{
  "Goal 1 Rating": "yellow",
  "Goal 2 Rating": "red",
  "Goal 3 Rating": "orange",
  "Goal 4 Rating": "yellow",
  "Goal 5 Rating": "orange",
  "Goal 6 Rating": "orange",
  "Goal 7 Rating": "yellow",
  "Goal 8 Rating": "yellow",
  "Goal 9 Rating": "yellow",
  "Goal 10 Rating": "yellow",
  "Goal 11 Rating": "yellow",
  "Goal 12 Rating": "red",
  "Goal 13 Rating": "red",
  "Goal 14 Rating": "orange",
  "Goal 15 Rating": "red",
  "Goal 16 Rating": "orange",
  "Goal 17 Rating": "orange",
  "Goal 1 Score": 99.5865,
  "Goal 2 Score": 66.578625,
  "Goal 3 Score": 94.9493571428571,
  "Goal 4 Score": 93.2583333333333,
  "Goal 5 Score": 83.5895,
  "Goal 6 Score": 83.8546,
  "Goal 7 Score": 81.36025,
  "Goal 8 Score": 80.8847142857143,
  "Goal 9 Score": 88.0832857142857,
  "Goal 10 Score": 89.397,
  "Goal 11 Score": 97.4465,
  "Goal 12 Score": 53.1488571428571,
  "Goal 13 Score": 48.8506666666667,
  "Goal 14 Score": 61.7915,
  "Goal 15 Score": 61.3198,
  "Goal 16 Score": 82.9563636363636,
  "Goal 17 Score": 73.0322
}