{
  "Goal 1 Rating": "green",
  "Goal 2 Rating": "red",
  "Goal 3 Rating": "orange",
  "Goal 4 Rating": "orange",
  "Goal 5 Rating": "orange",
  "Goal 6 Rating": "yellow",
  "Goal 7 Rating": "orange",
  "Goal 8 Rating": "yellow",
  "Goal 9 Rating": "orange",
  "Goal 10 Rating": "yellow",
  "Goal 11 Rating": "yellow",
  "Goal 12 Rating": "red",
  "Goal 13 Rating": "orange",
  "Goal 14 Rating": "gray",
  "Goal 15 Rating": "yellow",
  "Goal 16 Rating": "orange",
  "Goal 17 Rating": "red",
  "Goal 1 Score": 98.922,
  "Goal 2 Score": 65.1165,
  "Goal 3 Score": 84.1684615384615,
  "Goal 4 Score": 94.1235,
  "Goal 5 Score": 66.66925,
  "Goal 6 Score": 86.5838,
  "Goal 7 Score": 75.118,
  "Goal 8 Score": 80.2835714285714,
  "Goal 9 Score": 81.2215714285714,
  "Goal 10 Score": 94.089,
  "Goal 11 Score": 96.42675,
  "Goal 12 Score": 68.9547142857143,
  "Goal 13 Score": 83.9773333333333,
  "Goal 14 Score": null,
  "Goal 15 Score": 86.0832,
  "Goal 16 Score": 69.7643636363636,
  "Goal 17 Score": 54.387
}