[
  {
    "title": "afghanistan vs zimbabwe",
    "link": "https://trends.google.com/trending/rss?geo=IQ",
    "pubdate": "Wed, 11 Dec 2024 04:10:00 -0800",
    "approx_traffic": 200,
    "picture": "https://encrypted-tbn2.gstatic.com/images?q=tbn:ANd9GcTMopSo2LJrHCNpvu8ylEPmydj1EGRwwz1EEPIto_j55Ml2ahJ0QFOdy7iVOZk",
    "picture_source": "ESPNcricinfo",
    "news_items": [
      {
        "title": "Mujeeb returns for Afghanistan as visitors bat first in Harare",
        "snippet": "",
        "url": "https://www.espncricinfo.com/series/afghanistan-in-zimbabwe-2024-25-1457916/zimbabwe-vs-afghanistan-1st-t20i-1457920/match-report",
        "picture": "https://encrypted-tbn2.gstatic.com/images?q=tbn:ANd9GcTMopSo2LJrHCNpvu8ylEPmydj1EGRwwz1EEPIto_j55Ml2ahJ0QFOdy7iVOZk",
        "source": "ESPNcricinfo"
      },
      {
        "title": "Zimbabwe vs Afghanistan Live Score: It’s a Four. Zimbabwe at 4/0 after 1.1 overs",
        "snippet": "",
        "url": "https://www.hindustantimes.com/cricket/zimbabwe-vs-afghanistan-live-score-1st-t20i-of-afghanistan-tour-of-zimbabwe-2024-25-final-updates-today-11-dec-2024-101733912999919.html",
        "picture": "https://encrypted-tbn2.gstatic.com/images?q=tbn:ANd9GcTEaqH0oC3TK15tfy3IrmQCB0QOr9Jq9x21LZOjGGAyOUf4Etw0GkhQelB4pVo",
        "source": "Hindustan Times"
      },
      {
        "title": "Harare Sports Club Harare Weather Report For AFG Vs ZIM 1st T20I",
        "snippet": "",
        "url": "https://cricket.one/match-hub/harare-sports-club-harare-weather-report-for-afg-vs-zim-1st-t20i/67581f30703dbcd7d84a2c84",
        "picture": "https://encrypted-tbn0.gstatic.com/images?q=tbn:ANd9GcQ_h0P8iUGCNSAlOueWYLOi6yzPWuCI_jdBkAAadr3r88rbaGjnurny0gSe5xs",
        "source": "cricket.one"
      }
    ]
  },
  {
    "title": "رنا سماحة",
    "link": "https://trends.google.com/trending/rss?geo=IQ",
    "pubdate": "Wed, 11 Dec 2024 04:00:00 -0800",
    "approx_traffic": 200,
    "picture": "https://encrypted-tbn1.gstatic.com/images?q=tbn:ANd9GcSSxe5JN09et1MzooNX5q6Cqm2rsPwne3jyCr6Qr4VDrO75RhvQK_jKcTqDqOg",
    "picture_source": "Alsumaria",
    "news_items": [
      {
        "title": "انفصالها عن زوجها للمرة الثانية.. الفنانة رنا سماحة تتصدر الترند",
        "snippet": "",
        "url": "https://www.alsumaria.tv/news/artculture/509163/%D8%A7%D9%86%D9%81%D8%B5%D8%A7%D9%84%D9%87%D8%A7-%D8%B9%D9%86-%D8%B2%D9%88%D8%AC%D9%87%D8%A7-%D9%84%D9%84%D9%85%D8%B1%D8%A9-%D8%A7%D9%84%D8%AB%D8%A7%D9%86%D9%8A%D8%A9-%D8%A7%D9%84%D9%81%D9%86%D8%A7%D9%86%D8%A9-%D8%B1%D9%86%D8%A7-%D8%B3%D9%85%D8%A7%D8%AD%D8%A9-%D8%AA%D8%AA%D8%B5%D8%AF%D8%B1-%D8%A7%D9%84%D8%AA%D8%B1%D9%86%D8%AF",
        "picture": "https://encrypted-tbn1.gstatic.com/images?q=tbn:ANd9GcSSxe5JN09et1MzooNX5q6Cqm2rsPwne3jyCr6Qr4VDrO75RhvQK_jKcTqDqOg",
        "source": "Alsumaria"
      },
      {
        "title": "رنا سماحة تردّ على جدل انفصالها عن زوجها",
        "snippet": "",
        "url": "https://www.lahamag.com/article/218317-%D8%B1%D9%86%D8%A7-%D8%B3%D9%85%D8%A7%D8%AD%D8%A9-%D8%AA%D8%B1%D8%AF-%D8%B9%D9%84%D9%89-%D8%AC%D8%AF%D9%84-%D8%A7%D9%86%D9%81%D8%B5%D8%A7%D9%84%D9%87%D8%A7-%D8%B9%D9%86-%D8%B2%D9%88%D8%AC%D9%87%D8%A7",
        "picture": "https://encrypted-tbn2.gstatic.com/images?q=tbn:ANd9GcSAkjsoZn94N1DvJgky9KA-0x5_e-7dqhIOmL73uJB1zTArUvTo6nQNOBoFNMI",
        "source": "Laha Magazine"
      },
      {
        "title": "رنا سماحة تعلن إصابة ابنها بهذا الفيروس الخطير",
        "snippet": "",
        "url": "https://www.akhbar-sharq.com/news/26405",
        "picture": "https://encrypted-tbn0.gstatic.com/images?q=tbn:ANd9GcTVRJzPejY3AxYqcGFUAxeWzysZysP6Dujl0-PxQ_Jsovtg8IHiIFrdq4pFJcs",
        "source": "شبكة أخبار الشرق"
      }
    ]
  },
  {
    "title": "موعد امتحانات الترم الأول",
    "link": "https://trends.google.com/trending/rss?geo=IQ",
    "pubdate": "Wed, 11 Dec 2024 01:10:00 -0800",
    "approx_traffic": 200,
    "picture": "https://encrypted-tbn0.gstatic.com/images?q=tbn:ANd9GcRPe5PZkvmOLhZl1QXj1hbBIJlkWV9GWPF2l_E0X0-XwT3H6s7SWZNVsdfpqy8",
    "picture_source": "إقرأ نيوز",
    "news_items": [
      {
        "title": "إجازة رسمية 4 أيام وراء بعض.. وزارة التربية والتعليم تفرح جميع الطلاب والمعلمين بهذا القرار الرسمي - إقرأ نيوز",
        "snippet": "",
        "url": "https://iq.iqraa.news/966239/%D8%A5%D8%AC%D8%A7%D8%B2%D8%A9-%D8%B1%D8%B3%D9%85%D9%8A%D8%A9-4-%D8%A3%D9%8A%D8%A7%D9%85-%D9%88%D8%B1%D8%A7%D8%A1-%D8%A8%D8%B9%D8%B6-%D9%88%D8%B2%D8%A7%D8%B1%D8%A9-%D8%A7%D9%84%D8%AA%D8%B1%D8%A8/",
        "picture": "https://encrypted-tbn0.gstatic.com/images?q=tbn:ANd9GcRPe5PZkvmOLhZl1QXj1hbBIJlkWV9GWPF2l_E0X0-XwT3H6s7SWZNVsdfpqy8",
        "source": "إقرأ نيوز"
      },
      {
        "title": "تعطيل الدراسة 4 أيام متواصلة.. مفاجأة للطلاب والمعلمين بجميع المدارس في هذا الموعد",
        "snippet": "",
        "url": "https://zahraa.mr/3694793/%D8%AA%D8%B9%D8%B7%D9%8A%D9%84-%D8%A7%D9%84%D8%AF%D8%B1%D8%A7%D8%B3%D8%A9-4-%D8%A3%D9%8A%D8%A7%D9%85-%D9%85%D8%AA%D9%88%D8%A7%D8%B5%D9%84%D8%A9-%D9%85%D9%81%D8%A7%D8%AC%D8%A3%D8%A9-%D9%84%D9%84/",
        "picture": "https://encrypted-tbn0.gstatic.com/images?q=tbn:ANd9GcSc1lAJ4e0yZ9Fp3sWsuMXnPb0KPaX8oSzp-UpoQ14cWiSfpdP3igmtQRVXgDA",
        "source": "zahraa.mr"
      },
      {
        "title": "متي مواعيد امتحانات نصف العام الدراسي في مصر 2024 - المساء الاخباري",
        "snippet": "",
        "url": "https://newsy.almesasports.com/352861/%D9%85%D9%88%D8%A7%D8%B9%D9%8A%D8%AF-%D8%A7%D9%85%D8%AA%D8%AD%D8%A7%D9%86%D8%A7%D8%AA-%D9%86%D8%B5%D9%81-%D8%A7%D9%84%D8%B9%D8%A7%D9%85-%D8%A7%D9%84%D8%AF%D8%B1%D8%A7%D8%B3%D9%8A-2/",
        "picture": "https://encrypted-tbn1.gstatic.com/images?q=tbn:ANd9GcQKZ9e0CR1OgK93cQSTQtEV9dnx7zRzXCam-cd1hAECOS9VezA57lBFP94_Teg",
        "source": "المساء الاخباري"
      }
    ]
  },
  {
    "title": "جمال سليمان",
    "link": "https://trends.google.com/trending/rss?geo=IQ",
    "pubdate": "Tue, 10 Dec 2024 23:40:00 -0800",
    "approx_traffic": 500,
    "picture": "https://encrypted-tbn2.gstatic.com/images?q=tbn:ANd9GcTZ5Oxotsw3DcSxeHf89Ri18J6V0ezUFmXHeaLAat7RLSqDOOVWRy1mxhHlQz0",
    "picture_source": "Masrawy",
    "news_items": [
      {
        "title": "حدث بالفن| خطوبة فنانة ونقل منى فاروق المستشفى وجمال سليمان يعلن نيته الترشح لرئاسة سوريا",
        "snippet": "",
        "url": "https://www.masrawy.com/arts/zoom/details/2024/12/11/2689675/%D8%AD%D8%AF%D8%AB-%D8%A8%D8%A7%D9%84%D9%81%D9%86-%D8%AE%D8%B7%D9%88%D8%A8%D8%A9-%D9%81%D9%86%D8%A7%D9%86%D8%A9-%D9%88%D9%86%D9%82%D9%84-%D9%85%D9%86%D9%89-%D9%81%D8%A7%D8%B1%D9%88%D9%82-%D8%A7%D9%84%D9%85%D8%B3%D8%AA%D8%B4%D9%81%D9%89-%D9%88%D8%AC%D9%85%D8%A7%D9%84-%D8%B3%D9%84%D9%8A%D9%85%D8%A7%D9%86-%D9%8A%D8%B9%D9%84%D9%86-%D9%86%D9%8A%D8%AA%D9%87-%D8%A7%D9%84%D8%AA%D8%B1%D8%B4%D8%AD-%D9%84%D8%B1%D8%A6%D8%A7%D8%B3%D8%A9-%D8%B3%D9%88%D8%B1%D9%8A%D8%A7",
        "picture": "https://encrypted-tbn2.gstatic.com/images?q=tbn:ANd9GcTZ5Oxotsw3DcSxeHf89Ri18J6V0ezUFmXHeaLAat7RLSqDOOVWRy1mxhHlQz0",
        "source": "Masrawy"
      },
      {
        "title": "جمال سليمان لـ\"العربية\": قد أترشح لرئاسة سوريا",
        "snippet": "",
        "url": "https://www.alarabiya.net/arab-and-world/syria/2024/12/10/%D8%AC%D9%85%D8%A7%D9%84-%D8%B3%D9%84%D9%8A%D9%85%D8%A7%D9%86-%D9%84%D9%80-%D8%A7%D9%84%D8%B9%D8%B1%D8%A8%D9%8A%D8%A9-%D9%82%D8%AF-%D8%A3%D8%AA%D8%B1%D8%B4%D8%AD-%D9%84%D8%B1%D8%A6%D8%A7%D8%B3%D8%A9-%D8%B3%D9%88%D8%B1%D9%8A%D8%A7",
        "picture": "https://encrypted-tbn0.gstatic.com/images?q=tbn:ANd9GcSEDPqooryaNFvWmx7iv_vyuX6V5Qy9vEsCIXQ_VjpgG1mH3JPnFiknEuzRGGk",
        "source": "العربية"
      },
      {
        "title": "\"خروج مذل للأسد\".. الفنان جمال سليمان يتحدث عن رؤيته لسوريا الجديدة | التلفزيون العربي",
        "snippet": "",
        "url": "https://www.alaraby.com/news/%D8%AE%D8%B1%D9%88%D8%AC-%D9%85%D8%B0%D9%84-%D9%84%D9%84%D8%A3%D8%B3%D8%AF-%D8%A7%D9%84%D9%81%D9%86%D8%A7%D9%86-%D8%AC%D9%85%D8%A7%D9%84-%D8%B3%D9%84%D9%8A%D9%85%D8%A7%D9%86-%D9%8A%D8%AA%D8%AD%D8%AF%D8%AB-%D8%B9%D9%86-%D8%B1%D8%A4%D9%8A%D8%AA%D9%87-%D9%84%D8%B3%D9%88%D8%B1%D9%8A%D8%A7-%D8%A7%D9%84%D8%AC%D8%AF%D9%8A%D8%AF%D8%A9",
        "picture": "https://encrypted-tbn0.gstatic.com/images?q=tbn:ANd9GcSSIAJtN98pFkVxSWDS9dEm9n0WSkgYyTMoS-BQGVWwuFBB5-mrEX0K4TdqIHs",
        "source": "التلفزيون العربي"
      }
    ]
  },
  {
    "title": "هضبة الجولان",
    "link": "https://trends.google.com/trending/rss?geo=IQ",
    "pubdate": "Tue, 10 Dec 2024 23:10:00 -0800",
    "approx_traffic": 500,
    "picture": "https://encrypted-tbn2.gstatic.com/images?q=tbn:ANd9GcR_6HIhvMFeTpQlnPNUT5TlLlw7qW4DOYMhAcOQwJakLWt3ct5TcKbVYiT0TIM",
    "picture_source": "سكاي نيوز عربية",
    "news_items": [
      {
        "title": "إسرائيل على أبواب دمشق.. ونفي لمغادرة \"المنطقة العازلة\"",
        "snippet": "",
        "url": "https://www.skynewsarabia.com/middle-east/1761010-%D8%A7%D9%95%D8%B3%D8%B1%D8%A7%D9%8A%D9%94%D9%8A%D9%84-%D8%A7%D9%94%D8%A8%D9%88%D8%A7%D8%A8-%D8%AF%D9%85%D8%B4%D9%82-%D9%88%D9%86%D9%81%D9%8A-%D9%84%D9%85%D8%BA%D8%A7%D8%AF%D8%B1%D8%A9-%D8%A7%D9%84%D9%85%D9%86%D8%B7%D9%82%D8%A9-%D8%A7%D9%84%D8%B9%D8%A7%D8%B2%D9%84%D8%A9",
        "picture": "https://encrypted-tbn2.gstatic.com/images?q=tbn:ANd9GcR_6HIhvMFeTpQlnPNUT5TlLlw7qW4DOYMhAcOQwJakLWt3ct5TcKbVYiT0TIM",
        "source": "سكاي نيوز عربية"
      },
      {
        "title": "مصر تبلغ واشنطن رفضها استيلاء إسرائيل على المنطقة العازلة مع سوريا",
        "snippet": "",
        "url": "https://www.aljazeera.net/news/2024/12/11/%D9%85%D8%B5%D8%B1-%D8%AA%D8%A8%D9%84%D8%BA-%D9%88%D8%A7%D8%B4%D9%86%D8%B7%D9%86-%D8%B1%D9%81%D8%B6%D9%87%D8%A7-%D8%A7%D8%B3%D8%AA%D9%8A%D9%84%D8%A7%D8%A1-%D8%A5%D8%B3%D8%B1%D8%A7%D8%A6%D9%8A%D9%84",
        "picture": "https://encrypted-tbn1.gstatic.com/images?q=tbn:ANd9GcQjPE_iWrRf9k2LFZ1NfKEgid8DXF7ivTLPF1xMvczyd3Z8azRluuKSCXxSGxQ",
        "source": "الجزيرة نت"
      },
      {
        "title": "الإمارات تعلق على \"خرق إسرائيل\" لاتفاقية فض الاشتباك",
        "snippet": "",
        "url": "https://www.alhurra.com/uae/2024/12/10/%D8%A7%D9%84%D8%A5%D9%85%D8%A7%D8%B1%D8%A7%D8%AA-%D8%AA%D8%B9%D9%84%D9%82-%D8%AE%D8%B1%D9%82-%D8%A5%D8%B3%D8%B1%D8%A7%D8%A6%D9%8A%D9%84-%D9%84%D8%A7%D8%AA%D9%81%D8%A7%D9%82%D9%8A%D8%A9-%D9%81%D8%B6-%D8%A7%D9%84%D8%A7%D8%B4%D8%AA%D8%A8%D8%A7%D9%83",
        "picture": "https://encrypted-tbn2.gstatic.com/images?q=tbn:ANd9GcTmSbWSb02j4cOj8aukwotmOkpqUQo_vhkjAymkHkWYbGytM6_G6a15J18Z5Uo",
        "source": "الحرة"
      }
    ]
  },
  {
    "title": "واتساب",
    "link": "https://trends.google.com/trending/rss?geo=IQ",
    "pubdate": "Tue, 10 Dec 2024 21:50:00 -0800",
    "approx_traffic": 500,
    "picture": "https://encrypted-tbn2.gstatic.com/images?q=tbn:ANd9GcSAlzI05y4TDFhw2gMICfvIet5V5b20GbjS2IHpKrT9K5goIpb_sl6wjPshWBQ",
    "picture_source": "العربية",
    "news_items": [
      {
        "title": "\"واتساب\" يصلح خللاً يتعلق بخاصية \"العرض مرة واحدة\"",
        "snippet": "",
        "url": "https://www.alarabiya.net/technology/2024/12/09/-%D9%88%D8%A7%D8%AA%D8%B3%D8%A7%D8%A8-%D9%8A%D8%B5%D9%84%D8%AD-%D8%AE%D9%84%D9%84%D9%8B%D8%A7-%D9%8A%D8%AA%D8%B9%D9%84%D9%82-%D8%A8%D8%AE%D8%A7%D8%B5%D9%8A%D8%A9-%D8%A7%D9%84%D8%B9%D8%B1%D8%B6-%D9%85%D8%B1%D8%A9-%D9%88%D8%A7%D8%AD%D8%AF%D8%A9-",
        "picture": "https://encrypted-tbn2.gstatic.com/images?q=tbn:ANd9GcSAlzI05y4TDFhw2gMICfvIet5V5b20GbjS2IHpKrT9K5goIpb_sl6wjPshWBQ",
        "source": "العربية"
      },
      {
        "title": "تحديث جديد من واتسآب لحماية خصوصية المستخدمين",
        "snippet": "",
        "url": "https://www.msn.com/ar-sa/news/techandscience/%D8%AA%D8%AD%D8%AF%D9%8A%D8%AB-%D8%AC%D8%AF%D9%8A%D8%AF-%D9%85%D9%86-%D9%88%D8%A7%D8%AA%D8%B3%D8%A2%D8%A8-%D9%84%D8%AD%D9%85%D8%A7%D9%8A%D8%A9-%D8%AE%D8%B5%D9%88%D8%B5%D9%8A%D8%A9-%D8%A7%D9%84%D9%85%D8%B3%D8%AA%D8%AE%D8%AF%D9%85%D9%8A%D9%86/ar-AA1vENMy",
        "picture": "https://encrypted-tbn0.gstatic.com/images?q=tbn:ANd9GcT_xqlVK-2CO59koH63w6spqf-GDqf64ssWMYA7r0WC1s-nwAjdu9CUamM4Ftg",
        "source": "MSN"
      },
      {
        "title": "مفاجأة سارة من شركة ميتا للمستخدمين بخصوص اصلاح الخلل التقني للواتساب لميزة العرض لمرة واحدة",
        "snippet": "",
        "url": "https://alkhabarkw.com/technology/%D8%A7%D8%B5%D9%84%D8%A7%D8%AD-%D8%A7%D9%84%D8%AE%D9%84%D9%84-%D8%A7%D9%84%D8%AA%D9%82%D9%86%D9%8A-%D9%84%D9%84%D9%88%D8%A7%D8%AA%D8%B3%D8%A7%D8%A8/144041/",
        "picture": "https://encrypted-tbn1.gstatic.com/images?q=tbn:ANd9GcRod2d6jdKgptZ2ooNVb38QPpujsKbxftTXRpz0Ub1p8f0R5kavdy50I1B6au0",
        "source": "alkhabarkw.com"
      }
    ]
  },
  {
    "title": "محمد سعيد رمضان البوطي",
    "link": "https://trends.google.com/trending/rss?geo=IQ",
    "pubdate": "Tue, 10 Dec 2024 17:00:00 -0800",
    "approx_traffic": 200,
    "picture": "https://encrypted-tbn0.gstatic.com/images?q=tbn:ANd9GcThM0fstl8PaPdhpC5YtAJzAM6VzgV0GXZNFFYrUlsR4S5lTakIaEKfNA48SC4",
    "picture_source": "إرم نيوز",
    "news_items": [
      {
        "title": "تضارب الأنباء عن مقتل الشيخ توفيق البوطي في دمشق",
        "snippet": "",
        "url": "https://www.eremnews.com/news/arab-world/xn4df3d",
        "picture": "https://encrypted-tbn0.gstatic.com/images?q=tbn:ANd9GcThM0fstl8PaPdhpC5YtAJzAM6VzgV0GXZNFFYrUlsR4S5lTakIaEKfNA48SC4",
        "source": "إرم نيوز"
      },
      {
        "title": "تضارب الأنباء حول مصير الشيخ توفيق البوطى فى سوريا",
        "snippet": "",
        "url": "https://m2.youm7.com/story/2024/12/11/%D8%AA%D8%B6%D8%A7%D8%B1%D8%A8-%D8%A7%D9%84%D8%A3%D9%86%D8%A8%D8%A7%D8%A1-%D8%AD%D9%88%D9%84-%D9%85%D8%B5%D9%8A%D8%B1-%D8%A7%D9%84%D8%B4%D9%8A%D8%AE-%D8%AA%D9%88%D9%81%D9%8A%D9%82-%D8%A7%D9%84%D8%A8%D9%88%D8%B7%D9%89-%D9%81%D9%89-%D8%B3%D9%88%D8%B1%D9%8A%D8%A7/6807884",
        "picture": "https://encrypted-tbn0.gstatic.com/images?q=tbn:ANd9GcRW5f4gM6we4ipMq2--3AFAJdjmIxfq6Fs6hHEv-0s1CWu3QAB-gwzrVrAsuzs",
        "source": "اليوم السابع"
      },
      {
        "title": "شيخ مقرب من الأسد سابقا يعلن دعمه لـ\"هيئة تحرير الشام\".. من هو توفيق البوطي؟",
        "snippet": "",
        "url": "https://almashhad.com/article/773112298002792-News/496229365573452-%D8%B4%D9%8A%D8%AE-%D9%85%D9%82%D8%B1%D8%A8-%D9%85%D9%86-%D8%A7%D9%84%D8%A3%D8%B3%D8%AF-%D8%B3%D8%A7%D8%A8%D9%82%D8%A7-%D9%8A%D8%B9%D9%84%D9%86-%D8%AF%D8%B9%D9%85%D9%87-%D9%84%D9%87%D9%8A%D8%A6%D8%A9-%D8%AA%D8%AD%D8%B1%D9%8A%D8%B1-%D8%A7%D9%84%D8%B4%D8%A7%D9%85-%D9%85%D9%86-%D9%87%D9%88-%D8%AA%D9%88%D9%81%D9%8A%D9%82-%D8%A7%D9%84%D8%A8%D9%88%D8%B7%D9%8A/",
        "picture": "https://encrypted-tbn2.gstatic.com/images?q=tbn:ANd9GcSMiQ3peG87aci4cO9KxGEtQR70Rrm-tBO2dhSxs55zRWMMTKCD1UwAGurMxmI",
        "source": "قناة ومنصة المشهد"
      }
    ]
  },
  {
    "title": "apple ios 18.2 release date",
    "link": "https://trends.google.com/trending/rss?geo=IQ",
    "pubdate": "Tue, 10 Dec 2024 16:30:00 -0800",
    "approx_traffic": 100,
    "picture": "https://encrypted-tbn3.gstatic.com/images?q=tbn:ANd9GcQOx-1qdZI_C6RbVnBEXdm_DPexHIDMKzGJOaT68zpv0x9B4320mvATiwnwKks",
    "picture_source": "Apple",
    "news_items": [
      {
        "title": "Apple Intelligence now features Image Playground, Genmoji, and more",
        "snippet": "",
        "url": "https://www.apple.com/newsroom/2024/12/apple-intelligence-now-features-image-playground-genmoji-and-more/",
        "picture": "https://encrypted-tbn3.gstatic.com/images?q=tbn:ANd9GcQOx-1qdZI_C6RbVnBEXdm_DPexHIDMKzGJOaT68zpv0x9B4320mvATiwnwKks",
        "source": "Apple"
      },
      {
        "title": "Apple iOS 18.2 Release Date: iPhone’s New Free Upgrade Is Hours Away",
        "snippet": "",
        "url": "https://www.forbes.com/sites/davidphelan/2024/12/09/ios-182-release-date-iphones-biggest-ever-upgrade-is-hours-away/",
        "picture": "https://encrypted-tbn3.gstatic.com/images?q=tbn:ANd9GcQCN6oqOS07xjJeG8orHw4WCWa_3EvSnPvJdzayAWXfv6WUBeV_dFc1UzCzLyc",
        "source": "Forbes"
      },
      {
        "title": "Everything You Need to Know About Visual Intelligence on iPhone 16",
        "snippet": "",
        "url": "https://blogdoiphone.com/en/news/visual-intelligence-iphone-16/",
        "picture": "https://encrypted-tbn1.gstatic.com/images?q=tbn:ANd9GcRDP6kmInHtogfLF7qt9RT-XXwkYWfbaHg1ZXTqSkWAPZiRqr6QOYmN8A3niww",
        "source": "Blog do iPhone"
      }
    ]
  },
  {
    "title": "سوريا بشار الأسد",
    "link": "https://trends.google.com/trending/rss?geo=IQ",
    "pubdate": "Tue, 10 Dec 2024 15:20:00 -0800",
    "approx_traffic": 100,
    "picture": "https://encrypted-tbn3.gstatic.com/images?q=tbn:ANd9GcROzJ0AK1PY5rdVQkVcw2pHQfvAkcgi9JzSlHlEzLBlzpHTdrsB8au_3zVMkwE",
    "picture_source": "سكاي نيوز عربية",
    "news_items": [
      {
        "title": "أمر بحل الجيش ورفض خطاب التنحي.. ساعات الأسد الأخيرة في دمشق",
        "snippet": "",
        "url": "https://www.skynewsarabia.com/middle-east/1761419-%D8%A7%D9%94%D9%85%D8%B1-%D8%A8%D8%AD%D9%84-%D8%A7%D9%84%D8%AC%D9%8A%D8%B4-%D9%88%D8%B1%D9%81%D8%B6-%D8%AE%D8%B7%D8%A7%D8%A8-%D8%A7%D9%84%D8%AA%D9%86%D8%AD%D9%8A-%D8%B3%D8%A7%D8%B9%D8%A7%D8%AA-%D8%A7%D9%84%D8%A7%D9%94%D8%B3%D8%AF-%D8%A7%D9%84%D8%A7%D9%94%D8%AE%D9%8A%D8%B1%D8%A9-%D8%AF%D9%85%D8%B4%D9%82",
        "picture": "https://encrypted-tbn3.gstatic.com/images?q=tbn:ANd9GcROzJ0AK1PY5rdVQkVcw2pHQfvAkcgi9JzSlHlEzLBlzpHTdrsB8au_3zVMkwE",
        "source": "سكاي نيوز عربية"
      },
      {
        "title": "مسؤولون روس: موسكو دفعت الأسد للفرار بعد تأكد هزيمته",
        "snippet": "",
        "url": "https://www.aljazeera.net/news/2024/12/11/%D9%85%D8%B3%D8%A4%D9%88%D9%84%D9%88%D9%86-%D8%B1%D9%88%D8%B3-%D9%85%D9%88%D8%B3%D9%83%D9%88-%D8%AF%D9%81%D8%B9%D8%AA-%D8%A7%D9%84%D8%A3%D8%B3%D8%AF-%D9%84%D9%84%D9%81%D8%B1%D8%A7%D8%B1",
        "picture": "https://encrypted-tbn2.gstatic.com/images?q=tbn:ANd9GcTgRm4sTs3OYu7sFWv0qqvxOed6wBHbE3pApjS20rACN3DWXGcgWW76zNkGqdA",
        "source": "الجزيرة نت"
      },
      {
        "title": "\"مصير القذافي\".. تقرير يكشف اللحظة التي قررت فيها روسيا تهريب الأسد",
        "snippet": "",
        "url": "https://www.alhurra.com/syria/2024/12/11/%D9%85%D8%B5%D9%8A%D8%B1-%D8%A7%D9%84%D9%82%D8%B0%D8%A7%D9%81%D9%8A-%D8%AA%D9%82%D8%B1%D9%8A%D8%B1-%D9%8A%D9%83%D8%B4%D9%81-%D8%A7%D9%84%D9%84%D8%AD%D8%B8%D8%A9-%D9%82%D8%B1%D8%B1%D8%AA-%D9%81%D9%8A%D9%87%D8%A7-%D8%B1%D9%88%D8%B3%D9%8A%D8%A7-%D8%AA%D9%87%D8%B1%D9%8A%D8%A8-%D8%A7%D9%84%D8%A3%D8%B3%D8%AF",
        "picture": "https://encrypted-tbn3.gstatic.com/images?q=tbn:ANd9GcQtmSkZxWwtaEMaaxpsixrKuxA5gz5kmE_AzGUN0deHWDcYQk6eQW7A49-Vrf4",
        "source": "الحرة"
      }
    ]
  },
  {
    "title": "leverkusen vs inter",
    "link": "https://trends.google.com/trending/rss?geo=IQ",
    "pubdate": "Tue, 10 Dec 2024 14:00:00 -0800",
    "approx_traffic": 100,
    "picture": "https://encrypted-tbn2.gstatic.com/images?q=tbn:ANd9GcTxB_xKqST6ZNSKJAR2rj4YKvuJ3ImRPzK9OOxHqRD75weUqTjtuGAD3zg4jWQ",
    "picture_source": "Bundesliga News in English",
    "news_items": [
      {
        "title": "Mukiele comments after late winner",
        "snippet": "",
        "url": "https://bulinews.com/mukiele-comments-after-late-winner",
        "picture": "https://encrypted-tbn2.gstatic.com/images?q=tbn:ANd9GcTxB_xKqST6ZNSKJAR2rj4YKvuJ3ImRPzK9OOxHqRD75weUqTjtuGAD3zg4jWQ",
        "source": "Bundesliga News in English"
      },
      {
        "title": "Report – Two Defensive Stalwarts Unavailable For Lazio Vs Inter Milan Serie A Clash",
        "snippet": "",
        "url": "https://sempreinter.com/2024/12/11/francesco-acerbi-benjamin-pavard-unavailable-lazio-vs-inter-milan-serie-a-clash/",
        "picture": "https://encrypted-tbn1.gstatic.com/images?q=tbn:ANd9GcR7jsd9f-w2MUY_xtLVwvPmuMtnw_6WSVuGSfY2AWDQ6iwmsZTbg5swmT_i47E",
        "source": "SempreInter.com"
      },
      {
        "title": "Subpar Offensive Production Starting to Hinder Inter",
        "snippet": "",
        "url": "https://cultofcalcio.com/subpar-offensive-production-starting-to-hinder-inter/",
        "picture": "https://encrypted-tbn2.gstatic.com/images?q=tbn:ANd9GcQhHmhdXak2o8G1DwzcUk4Wilyx55U2kYOPuaNXr_uVgq0FEW3LVWv70PCc-14",
        "source": "The Cult of Calcio"
      }
    ]
  }
]