{
  "Goal 1 Rating": "green",
  "Goal 2 Rating": "orange",
  "Goal 3 Rating": "orange",
  "Goal 4 Rating": "orange",
  "Goal 5 Rating": "orange",
  "Goal 6 Rating": "orange",
  "Goal 7 Rating": "orange",
  "Goal 8 Rating": "orange",
  "Goal 9 Rating": "orange",
  "Goal 10 Rating": "orange",
  "Goal 11 Rating": "yellow",
  "Goal 12 Rating": "gray",
  "Goal 13 Rating": "yellow",
  "Goal 14 Rating": "red",
  "Goal 15 Rating": "red",
  "Goal 16 Rating": "orange",
  "Goal 17 Rating": "orange",
  "Goal 1 Score": 97.9305,
  "Goal 2 Score": 72.1955,
  "Goal 3 Score": 77.7885384615385,
  "Goal 4 Score": 83.3415,
  "Goal 5 Score": 51.2125,
  "Goal 6 Score": 71.04,
  "Goal 7 Score": 72.34575,
  "Goal 8 Score": 78.1178,
  "Goal 9 Score": 57.9108571428571,
  "Goal 10 Score": 65.339,
  "Goal 11 Score": 94.4855,
  "Goal 12 Score": 74.4903333333333,
  "Goal 13 Score": 91.8225,
  "Goal 14 Score": 48.9228333333333,
  "Goal 15 Score": 36.5463333333333,
  "Goal 16 Score": 64.0766666666667,
  "Goal 17 Score": 60.0442
}