{
  "Goal 1 Rating": "orange",
  "Goal 2 Rating": "orange",
  "Goal 3 Rating": "red",
  "Goal 4 Rating": "orange",
  "Goal 5 Rating": "orange",
  "Goal 6 Rating": "orange",
  "Goal 7 Rating": "orange",
  "Goal 8 Rating": "red",
  "Goal 9 Rating": "orange",
  "Goal 10 Rating": "red",
  "Goal 11 Rating": "red",
  "Goal 12 Rating": "green",
  "Goal 13 Rating": "yellow",
  "Goal 14 Rating": "red",
  "Goal 15 Rating": "red",
  "Goal 16 Rating": "red",
  "Goal 17 Rating": "orange",
  "Goal 1 Score": 81.01,
  "Goal 2 Score": 64.925,
  "Goal 3 Score": 60.0058571428572,
  "Goal 4 Score": 82.7435,
  "Goal 5 Score": 61.38075,
  "Goal 6 Score": 70.522,
  "Goal 7 Score": 58.91425,
  "Goal 8 Score": 69.4067142857143,
  "Goal 9 Score": 53.3935714285714,
  "Goal 10 Score": 49.44,
  "Goal 11 Score": 61.0145,
  "Goal 12 Score": 91.0604285714286,
  "Goal 13 Score": 95.4786666666667,
  "Goal 14 Score": 75.1426666666667,
  "Goal 15 Score": 57.8638,
  "Goal 16 Score": 49.5128,
  "Goal 17 Score": 65.2138
}