{
  "Goal 1 Rating": "red",
  "Goal 2 Rating": "red",
  "Goal 3 Rating": "red",
  "Goal 4 Rating": "red",
  "Goal 5 Rating": "orange",
  "Goal 6 Rating": "red",
  "Goal 7 Rating": "red",
  "Goal 8 Rating": "red",
  "Goal 9 Rating": "red",
  "Goal 10 Rating": "red",
  "Goal 11 Rating": "red",
  "Goal 12 Rating": "green",
  "Goal 13 Rating": "gray",
  "Goal 14 Rating": "gray",
  "Goal 15 Rating": "red",
  "Goal 16 Rating": "gray",
  "Goal 17 Rating": "red",
  "Goal 1 Score": 0,
  "Goal 2 Score": 25.7652857142857,
  "Goal 3 Score": 29.3647857142857,
  "Goal 4 Score": 1.23175,
  "Goal 5 Score": 55.73925,
  "Goal 6 Score": 41.8032,
  "Goal 7 Score": 12.47025,
  "Goal 8 Score": 51.8528333333333,
  "Goal 9 Score": 2.76033333333333,
  "Goal 10 Score": 32.901,
  "Goal 11 Score": 27.4563333333333,
  "Goal 12 Score": 95.31825,
  "Goal 13 Score": 99.155,
  "Goal 14 Score": null,
  "Goal 15 Score": 68.31775,
  "Goal 16 Score": 39.2574,
  "Goal 17 Score": 32.2115
}